topmodels/__init__.py
topmodels-0.0.0.dist-info/METADATA
topmodels-0.0.0.dist-info/WHEEL
topmodels-0.0.0.dist-info/licenses/LICENSE
topmodels-0.0.0.dist-info/RECORD
